<?xml version="1.0" ?>
    <data>
      <students>
            <student_full_name>Белов Марк Матвеевич</student_full_name>
            <student_group>021707</student_group>
            <student_valid_reason>5</student_valid_reason>
            <student_invalid_reason>2</student_invalid_reason>
        </students>
      <students>
            <student_full_name>Макаров Егор Владимирович</student_full_name>
            <student_group>021707</student_group>
            <student_valid_reason>3</student_valid_reason>
            <student_invalid_reason>0</student_invalid_reason>
        </students>
      <students>
            <student_full_name>Успенская Мирослава Давидовна</student_full_name>
            <student_group>0271705</student_group>
            <student_valid_reason>10</student_valid_reason>
            <student_invalid_reason>1</student_invalid_reason>
        </students>
      <students>
            <student_full_name>Верещагина Лидия Михайловна</student_full_name>
            <student_group>021707</student_group>
            <student_valid_reason>4</student_valid_reason>
            <student_invalid_reason>7</student_invalid_reason>
        </students>
      <students>
            <student_full_name>Кудряшова Александра Дмитриевна</student_full_name>
            <student_group>021706</student_group>
            <student_valid_reason>4</student_valid_reason>
            <student_invalid_reason>3</student_invalid_reason>
        </students>
      <students>
            <student_full_name>Макаров Кирилл Артёмович</student_full_name>
            <student_group>021706</student_group>
            <student_valid_reason>6</student_valid_reason>
            <student_invalid_reason>3</student_invalid_reason>
        </students>
      <students>
            <student_full_name>Филатов Иван Валерьевич</student_full_name>
            <student_group>021706</student_group>
            <student_valid_reason>10</student_valid_reason>
            <student_invalid_reason>3</student_invalid_reason>
        </students>
      <students>
            <student_full_name>Сорокина Сафия Григорьевна</student_full_name>
            <student_group>021707</student_group>
            <student_valid_reason>2</student_valid_reason>
            <student_invalid_reason>9</student_invalid_reason>
        </students>
      <students>
            <student_full_name>Золотарева Екатерина Михайловна</student_full_name>
            <student_group>021706</student_group>
            <student_valid_reason>8</student_valid_reason>
            <student_invalid_reason>9</student_invalid_reason>
        </students>
      <students>
            <student_full_name>Макарова Нина Кирилловна</student_full_name>
            <student_group>021706</student_group>
            <student_valid_reason>3</student_valid_reason>
            <student_invalid_reason>0</student_invalid_reason>
        </students>
      <students>
            <student_full_name>Сидоров Артём Богданович</student_full_name>
            <student_group>021706</student_group>
            <student_valid_reason>2</student_valid_reason>
            <student_invalid_reason>8</student_invalid_reason>
        </students>
      <students>
            <student_full_name>Иванова Сафия Тимофеевна</student_full_name>
            <student_group>0271705</student_group>
            <student_valid_reason>2</student_valid_reason>
            <student_invalid_reason>2</student_invalid_reason>
        </students>
      <students>
            <student_full_name>Колесников Матвей Андреевич</student_full_name>
            <student_group>021707</student_group>
            <student_valid_reason>0</student_valid_reason>
            <student_invalid_reason>4</student_invalid_reason>
        </students>
      <students>
            <student_full_name>Щербакова София Дмитриевна</student_full_name>
            <student_group>021707</student_group>
            <student_valid_reason>0</student_valid_reason>
            <student_invalid_reason>5</student_invalid_reason>
        </students>
      <students>
            <student_full_name>Белов Захар Вадимович</student_full_name>
            <student_group>0271705</student_group>
            <student_valid_reason>10</student_valid_reason>
            <student_invalid_reason>0</student_invalid_reason>
        </students>
      <students>
            <student_full_name>Сергеева Дарья Михайловна</student_full_name>
            <student_group>0271705</student_group>
            <student_valid_reason>6</student_valid_reason>
            <student_invalid_reason>5</student_invalid_reason>
        </students>
      <students>
            <student_full_name>Соловьев Михаил Игоревич</student_full_name>
            <student_group>021706</student_group>
            <student_valid_reason>8</student_valid_reason>
            <student_invalid_reason>0</student_invalid_reason>
        </students>
      <students>
            <student_full_name>Платонова Мирослава Георгиевна</student_full_name>
            <student_group>021707</student_group>
            <student_valid_reason>9</student_valid_reason>
            <student_invalid_reason>9</student_invalid_reason>
        </students>
      <students>
            <student_full_name>Кудрявцева Любовь Ярославовна</student_full_name>
            <student_group>021706</student_group>
            <student_valid_reason>7</student_valid_reason>
            <student_invalid_reason>4</student_invalid_reason>
        </students>
      <students>
            <student_full_name>Данилова Элина Данииловна</student_full_name>
            <student_group>021706</student_group>
            <student_valid_reason>9</student_valid_reason>
            <student_invalid_reason>6</student_invalid_reason>
        </students>
      <students>
            <student_full_name>Климова Мадина Александровна</student_full_name>
            <student_group>021707</student_group>
            <student_valid_reason>0</student_valid_reason>
            <student_invalid_reason>3</student_invalid_reason>
        </students>
      <students>
            <student_full_name>Алексеев Тимофей Демидович</student_full_name>
            <student_group>0271705</student_group>
            <student_valid_reason>6</student_valid_reason>
            <student_invalid_reason>6</student_invalid_reason>
        </students>
      <students>
            <student_full_name>Филиппова Василиса Максимовна</student_full_name>
            <student_group>021707</student_group>
            <student_valid_reason>2</student_valid_reason>
            <student_invalid_reason>2</student_invalid_reason>
        </students>
      <students>
            <student_full_name>Егоров Адам Тимофеевич</student_full_name>
            <student_group>021707</student_group>
            <student_valid_reason>9</student_valid_reason>
            <student_invalid_reason>10</student_invalid_reason>
        </students>
      <students>
            <student_full_name>Казаков Андрей Яковлевич</student_full_name>
            <student_group>021706</student_group>
            <student_valid_reason>7</student_valid_reason>
            <student_invalid_reason>3</student_invalid_reason>
        </students>
      <students>
            <student_full_name>Киселев Константин Александрович</student_full_name>
            <student_group>0271705</student_group>
            <student_valid_reason>2</student_valid_reason>
            <student_invalid_reason>3</student_invalid_reason>
        </students>
      <students>
            <student_full_name>Левин Михаил Григорьевич</student_full_name>
            <student_group>021706</student_group>
            <student_valid_reason>9</student_valid_reason>
            <student_invalid_reason>8</student_invalid_reason>
        </students>
      <students>
            <student_full_name>Никулин Платон Александрович</student_full_name>
            <student_group>021706</student_group>
            <student_valid_reason>4</student_valid_reason>
            <student_invalid_reason>4</student_invalid_reason>
        </students>
      <students>
            <student_full_name>Зиновьев Даниил Никитич</student_full_name>
            <student_group>0271705</student_group>
            <student_valid_reason>7</student_valid_reason>
            <student_invalid_reason>4</student_invalid_reason>
        </students>
      <students>
            <student_full_name>Сергеева Анастасия Константиновна</student_full_name>
            <student_group>021706</student_group>
            <student_valid_reason>6</student_valid_reason>
            <student_invalid_reason>3</student_invalid_reason>
        </students>
      <students>
            <student_full_name>Федотова Ирина Романовна</student_full_name>
            <student_group>021707</student_group>
            <student_valid_reason>1</student_valid_reason>
            <student_invalid_reason>3</student_invalid_reason>
        </students>
      <students>
            <student_full_name>Соловьев Дмитрий Макарович</student_full_name>
            <student_group>021707</student_group>
            <student_valid_reason>8</student_valid_reason>
            <student_invalid_reason>10</student_invalid_reason>
        </students>
      <students>
            <student_full_name>Тихонов Всеволод Никитич</student_full_name>
            <student_group>021706</student_group>
            <student_valid_reason>6</student_valid_reason>
            <student_invalid_reason>8</student_invalid_reason>
        </students>
      <students>
            <student_full_name>Кузьмина Кира Егоровна</student_full_name>
            <student_group>021707</student_group>
            <student_valid_reason>8</student_valid_reason>
            <student_invalid_reason>10</student_invalid_reason>
        </students>
      <students>
            <student_full_name>Гончарова Мария Фёдоровна</student_full_name>
            <student_group>0271705</student_group>
            <student_valid_reason>5</student_valid_reason>
            <student_invalid_reason>10</student_invalid_reason>
        </students>
      <students>
            <student_full_name>Соловьева Есения Михайловна</student_full_name>
            <student_group>021707</student_group>
            <student_valid_reason>6</student_valid_reason>
            <student_invalid_reason>1</student_invalid_reason>
        </students>
      <students>
            <student_full_name>Кузин Егор Даниилович</student_full_name>
            <student_group>021707</student_group>
            <student_valid_reason>9</student_valid_reason>
            <student_invalid_reason>6</student_invalid_reason>
        </students>
      <students>
            <student_full_name>Зайцев Марк Захарович</student_full_name>
            <student_group>021706</student_group>
            <student_valid_reason>6</student_valid_reason>
            <student_invalid_reason>7</student_invalid_reason>
        </students>
      <students>
            <student_full_name>Зайцева Юлия Романовна</student_full_name>
            <student_group>021707</student_group>
            <student_valid_reason>2</student_valid_reason>
            <student_invalid_reason>3</student_invalid_reason>
        </students>
      <students>
            <student_full_name>Малышева Арина Артемьевна</student_full_name>
            <student_group>021706</student_group>
            <student_valid_reason>0</student_valid_reason>
            <student_invalid_reason>8</student_invalid_reason>
        </students>
      <students>
            <student_full_name>Пахомова Варвара Тимофеевна</student_full_name>
            <student_group>021706</student_group>
            <student_valid_reason>5</student_valid_reason>
            <student_invalid_reason>0</student_invalid_reason>
        </students>
      <students>
            <student_full_name>Коровин Артём Артурович</student_full_name>
            <student_group>021706</student_group>
            <student_valid_reason>6</student_valid_reason>
            <student_invalid_reason>6</student_invalid_reason>
        </students>
      <students>
            <student_full_name>Козырева Виолетта Ильинична</student_full_name>
            <student_group>021707</student_group>
            <student_valid_reason>2</student_valid_reason>
            <student_invalid_reason>7</student_invalid_reason>
        </students>
      <students>
            <student_full_name>Васильева Виктория Данииловна</student_full_name>
            <student_group>021706</student_group>
            <student_valid_reason>6</student_valid_reason>
            <student_invalid_reason>9</student_invalid_reason>
        </students>
      <students>
            <student_full_name>Андреев Давид Андреевич</student_full_name>
            <student_group>0271705</student_group>
            <student_valid_reason>1</student_valid_reason>
            <student_invalid_reason>1</student_invalid_reason>
        </students>
      <students>
            <student_full_name>Петров Арсений Артёмович</student_full_name>
            <student_group>021706</student_group>
            <student_valid_reason>6</student_valid_reason>
            <student_invalid_reason>6</student_invalid_reason>
        </students>
      <students>
            <student_full_name>Поляков Роман Артёмович</student_full_name>
            <student_group>021706</student_group>
            <student_valid_reason>7</student_valid_reason>
            <student_invalid_reason>4</student_invalid_reason>
        </students>
      <students>
            <student_full_name>Назарова Камила Александровна</student_full_name>
            <student_group>021706</student_group>
            <student_valid_reason>4</student_valid_reason>
            <student_invalid_reason>6</student_invalid_reason>
        </students>
      <students>
            <student_full_name>Антонова Ксения Артёмовна</student_full_name>
            <student_group>021706</student_group>
            <student_valid_reason>5</student_valid_reason>
            <student_invalid_reason>1</student_invalid_reason>
        </students>
      <students>
            <student_full_name>Новиков Захар Давидович</student_full_name>
            <student_group>0271705</student_group>
            <student_valid_reason>2</student_valid_reason>
            <student_invalid_reason>8</student_invalid_reason>
      </students>
    </data>